{ "encrypted": "false", "address": "https://example.com/api/IncidentService", "hostName": "localhost", "severity": "INFO", "service": "IncidentService", "message": "<source name=\"example_3C273\" flux=\"0.0196\"><spectrum escale=\"MeV\"><particle name=\"gamma\"><power_law emin=\"20.0\" emax=\"200000.\" gamma=\"2.58\"/></particle><celestial_dir ra=\"187.25\" dec=\"2.17\"/></spectrum></source>", "operationName": "executeTest", "eventType": "REQ_IN", "messageDirection": "IN", "hostAddress": "127.0.0.1", "transport": "SOAP", "processId": "1", "customInfo": {}, "service_namespace": "http://foobar.example.com/test", "contentCut": false, "elapsed_timestamp_start": "2021-02-20T08:50:24.599Z", "application": "ExampleApp", "timestamp": "2021-02-20T07:00:00.000Z", "duration": 1.5 }
